sslcommerz_python/__init__.py
sslcommerz_python/_constants.py
sslcommerz_python/payment.py
sslcommerz_python-0.0.5.dist-info/LICENSE
sslcommerz_python-0.0.5.dist-info/METADATA
sslcommerz_python-0.0.5.dist-info/WHEEL
sslcommerz_python-0.0.5.dist-info/top_level.txt
sslcommerz_python-0.0.5.dist-info/RECORD
